udirect
